MANIFEST.in
README.md
README.rst
setupczornytomek.py
satup.egg-info/PKG-INFO
satup.egg-info/SOURCES.txt
satup.egg-info/dependency_links.txt
satup.egg-info/top_level.txt