Metadata-Version: 1.0
Name: satup
Version: 0.1.0
Summary: Super useful library
Home-page: UNKNOWN
Author: Tomaszek
Author-email: czornytomaszek@gmail.com
License: UNKNOWN
Platform: UNKNOWN
